milosmooth/__init__.py
milosmooth/modulo1.py
milosmooth-0.1.12.dist-info/METADATA
milosmooth-0.1.12.dist-info/WHEEL
milosmooth-0.1.12.dist-info/top_level.txt
milosmooth-0.1.12.dist-info/RECORD
