Metadata-Version: 2.1
Name: milosmooth
Version: 0.1.12
Summary: Libreria de suavizado de curvas
Home-page: https://gitlab.com/camilo.londonov
Author: Milo
Author-email: camilo.londonov@udea.edu.co
License: MIT
Platform: UNKNOWN
Requires-Python: >=3.10.12
Requires-Dist: matplotlib (==3.8.1)
Requires-Dist: numpy (==1.26.1)
Requires-Dist: pandas (==2.1.2)
